[{"aging_3_4":0,"aging_5":0,"material_SKU":21225693,"aging_0_1":1,"plant":"P01","buyer":null,"aging_2":2,"vendor":null},{"aging_3_4":2,"aging_5":2,"material_SKU":10458789,"aging_0_1":0,"plant":"P01","buyer":null,"aging_2":0,"vendor":null},{"aging_3_4":2,"aging_5":2,"material_SKU":15789456,"aging_0_1":1,"plant":"P02","buyer":null,"aging_2":1,"vendor":null},{"aging_3_4":2,"aging_5":2,"material_SKU":12345678,"aging_0_1":0,"plant":"P02","buyer":null,"aging_2":0,"vendor":null},{"aging_3_4":1,"aging_5":1,"material_SKU":10002365,"aging_0_1":1,"plant":"P01","buyer":"Galvo SA","aging_2":1,"vendor":null},{"aging_3_4":0,"aging_5":1,"material_SKU":14587959,"aging_0_1":0,"plant":"P01","buyer":"Galvo SA","aging_2":0,"vendor":null},{"aging_3_4":3,"aging_5":1,"material_SKU":14567983,"aging_0_1":2,"plant":"P02","buyer":"Investa PO","aging_2":2,"vendor":null},{"aging_3_4":4,"aging_5":0,"material_SKU":12587946,"aging_0_1":3,"plant":"P02","buyer":"Investa PO","aging_2":3,"vendor":null}]
