[{
	"plant": "ATS9",
	"plantDesc": "ATS9-GE Austria After Market",
	"aging11": 1,
	"aging2": 1,
	"aging34": 1,
	"aging5plus": 5,
	"totalReq": 5
},
{
	"plant": "ATW9",
	"plantDesc": "ATW9-GE Austria WHSE",
	"aging11": 1,
	"aging2": 1,
	"aging34": 1,
	"aging5plus": 1,
	"totalReq": 1
},
{
	"plant": "AUW1",
	"plantDesc": "AUW1-GEAU, Australia",
	"aging11": 1,
	"aging2": 1,
	"aging34": 1,
	"aging5plus": 53,
	"totalReq": 53
},
{
	"plant": "BE11",
	"plantDesc": "BE11-Belgium - Gent MFG Plant",
	"aging11": 265,
	"aging2": 21,
	"aging34": 135,
	"aging5plus": 611,
	"totalReq": 1131
},
{
	"plant": "BES1",
	"plantDesc": "BES1-Belgium After Market",
	"aging11": 4,
	"aging2": 96,
	"aging34": 1,
	"aging5plus": 8,
	"totalReq": 118
},
{
	"plant": "BEW1",
	"plantDesc": "BEW1-Belgium - Puurs WHSE",
	"aging11": 213,
	"aging2": 37,
	"aging34": 1,
	"aging5plus": 8,
	"totalReq": 258
},
{
	"plant": "CA11",
	"plantDesc": "CA11-Canada  Direct Ship",
	"aging11": 6,
	"aging2": 1,
	"aging34": 1,
	"aging5plus": 13,
	"totalReq": 19
},
{
	"plant": "CH19",
	"plantDesc": "CH19-UPS MFG Plant Switzerland",
	"aging11": 28,
	"aging2": 11,
	"aging34": 5,
	"aging5plus": 179,
	"totalReq": 223
},
{
	"plant": "CHS6",
	"plantDesc": "CHS6-UPS After Market Plant",
	"aging11": 1,
	"aging2": 3,
	"aging34": 4,
	"aging5plus": 5,
	"totalReq": 13
},
{
	"plant": "CHS9",
	"plantDesc": "CHS9-GEDE Riazzino Factory",
	"aging11": 61,
	"aging2": 158,
	"aging34": 1,
	"aging5plus": 58,
	"totalReq": 276
},
{
	"plant": "CHW7",
	"plantDesc": "CHW7-UPS Plant Moerdijk",
	"aging11": 27,
	"aging2": 28,
	"aging34": 2,
	"aging5plus": 2,
	"totalReq": 59
},
{
	"plant": "CHW8",
	"plantDesc": "CHW8-GE Consumer & Industrial SA",
	"aging11": 1,
	"aging2": 1,
	"aging34": 1,
	"aging5plus": 47,
	"totalReq": 49
},
{
	"plant": "CHW9",
	"plantDesc": "CHW9-GEDE-IMV Poland",
	"aging11": 1,
	"aging2": 1,
	"aging34": 1,
	"aging5plus": 1,
	"totalReq": 1
},
{
	"plant": "CL11",
	"plantDesc": "CL11-Chile GE International",
	"aging11": 23,
	"aging2": 9,
	"aging34": 1,
	"aging5plus": 91,
	"totalReq": 122
},
{
	"plant": "CN11",
	"plantDesc": "CN11-China SJV Components MFG",
	"aging11": 211,
	"aging2": 16,
	"aging34": 31,
	"aging5plus": 91,
	"totalReq": 347
},
{
	"plant": "CN12",
	"plantDesc": "CN12-China SJV Equipment MFG",
	"aging11": 144,
	"aging2": 11,
	"aging34": 19,
	"aging5plus": 286,
	"totalReq": 459
},
{
	"plant": "CNW1",
	"plantDesc": "CNW1-China WHSE - Bonded1",
	"aging11": 11,
	"aging2": 1,
	"aging34": 1,
	"aging5plus": 11,
	"totalReq": 21
},
{
	"plant": "CNW2",
	"plantDesc": "CNW2-China WHSE - Non Bonded2",
	"aging11": 72,
	"aging2": 19,
	"aging34": 11,
	"aging5plus": 53,
	"totalReq": 155
},
{
	"plant": "CNW4",
	"plantDesc": "CNW4-China WHSE - Bonded4",
	"aging11": 1,
	"aging2": 1,
	"aging34": 1,
	"aging5plus": 11,
	"totalReq": 13
},
{
	"plant": "CNW5",
	"plantDesc": "CNW5-China WHSE - Non Bonded5",
	"aging11": 2,
	"aging2": 1,
	"aging34": 1,
	"aging5plus": 1,
	"totalReq": 3
},
{
	"plant": "DE11",
	"plantDesc": "DE11-Neumünster MFG",
	"aging11": 1,
	"aging2": 37,
	"aging34": 1,
	"aging5plus": 11,
	"totalReq": 49
},
{
	"plant": "DES1",
	"plantDesc": "DES1-Germany Plant After Market",
	"aging11": 13,
	"aging2": 112,
	"aging34": 1,
	"aging5plus": 32,
	"totalReq": 147
},
{
	"plant": "DES9",
	"plantDesc": "DES9-UPS AS&S Germany",
	"aging11": 23,
	"aging2": 1,
	"aging34": 1,
	"aging5plus": 7,
	"totalReq": 31
},
{
	"plant": "DEW1",
	"plantDesc": "DEW1-Germany Plant Whse / TP",
	"aging11": 1,
	"aging2": 1,
	"aging34": 1,
	"aging5plus": 1,
	"totalReq": 2
},
{
	"plant": "DEW9",
	"plantDesc": "DEW9-UPS Subsidiary Germany",
	"aging11": 18,
	"aging2": 1,
	"aging34": 1,
	"aging5plus": 39,
	"totalReq": 57
},
{
	"plant": "ES11",
	"plantDesc": "ES11-Spain Terrassa MFG",
	"aging11": 9,
	"aging2": 2,
	"aging34": 1,
	"aging5plus": 174,
	"totalReq": 186
},
{
	"plant": "ESS1",
	"plantDesc": "ESS1-GE Power Controls Iberica SA&S",
	"aging11": 28,
	"aging2": 196,
	"aging34": 1,
	"aging5plus": 22,
	"totalReq": 246
},
{
	"plant": "ESS9",
	"plantDesc": "ESS9-UPS AS&S Spain",
	"aging11": 4,
	"aging2": 1,
	"aging34": 1,
	"aging5plus": 3,
	"totalReq": 7
},
{
	"plant": "ESW1",
	"plantDesc": "ESW1-GE Power Controls Iberica WHSE",
	"aging11": 65,
	"aging2": 9,
	"aging34": 1,
	"aging5plus": 4,
	"totalReq": 78
},
{
	"plant": "ESW9",
	"plantDesc": "ESW9-UPS Subsidiary  Spain",
	"aging11": 15,
	"aging2": 1,
	"aging34": 1,
	"aging5plus": 21,
	"totalReq": 35
},
{
	"plant": "FIW1",
	"plantDesc": "FIW1-Finland Plant Whse/ TP",
	"aging11": 2,
	"aging2": 1,
	"aging34": 2,
	"aging5plus": 115,
	"totalReq": 119
},
{
	"plant": "FRS1",
	"plantDesc": "FRS1-GE Power Controls France",
	"aging11": 71,
	"aging2": 122,
	"aging34": 1,
	"aging5plus": 17,
	"totalReq": 219
},
{
	"plant": "FRW1",
	"plantDesc": "FRW1-France Plant Whse / TP",
	"aging11": 1,
	"aging2": 1,
	"aging34": 1,
	"aging5plus": 21,
	"totalReq": 21
},
{
	"plant": "GBS1",
	"plantDesc": "GBS1-UK Plant After Market Servic",
	"aging11": 4,
	"aging2": 1,
	"aging34": 1,
	"aging5plus": 1,
	"totalReq": 5
},
{
	"plant": "GBS9",
	"plantDesc": "GBS9-UPS AS&S UK",
	"aging11": 5,
	"aging2": 1,
	"aging34": 1,
	"aging5plus": 12,
	"totalReq": 17
},
{
	"plant": "GBW1",
	"plantDesc": "GBW1-UK Plant Whse / TP",
	"aging11": 1,
	"aging2": 1,
	"aging34": 1,
	"aging5plus": 1,
	"totalReq": 1
},
{
	"plant": "GBW9",
	"plantDesc": "GBW9-UPS Subsidiary UK",
	"aging11": 2,
	"aging2": 1,
	"aging34": 1,
	"aging5plus": 5,
	"totalReq": 7
},
{
	"plant": "HU11",
	"plantDesc": "HU11-Ozd MFG Plant",
	"aging11": 448,
	"aging2": 45,
	"aging34": 131,
	"aging5plus": 998,
	"totalReq": 1622
},
{
	"plant": "HUW1",
	"plantDesc": "HUW1-Hungary - Nagykanizsa Whse",
	"aging11": 1,
	"aging2": 1,
	"aging34": 1,
	"aging5plus": 8,
	"totalReq": 8
},
{
	"plant": "HUW2",
	"plantDesc": "HUW2-Hungary - Gyál Whse",
	"aging11": 397,
	"aging2": 52,
	"aging34": 1,
	"aging5plus": 44,
	"totalReq": 494
},
{
	"plant": "IDW1",
	"plantDesc": "IDW1-PT. GE Operations Indonesia",
	"aging11": 1,
	"aging2": 1,
	"aging34": 1,
	"aging5plus": 24,
	"totalReq": 25
},
{
	"plant": "ITS1",
	"plantDesc": "ITS1-GE Power Cont Italia AS&S",
	"aging11": 29,
	"aging2": 16,
	"aging34": 1,
	"aging5plus": 3,
	"totalReq": 48
},
{
	"plant": "ITS9",
	"plantDesc": "ITS9-UPS AS&S Italy",
	"aging11": 8,
	"aging2": 1,
	"aging34": 1,
	"aging5plus": 11,
	"totalReq": 21
},
{
	"plant": "ITW9",
	"plantDesc": "ITW9-UPS Subsidiary Italy",
	"aging11": 1,
	"aging2": 1,
	"aging34": 1,
	"aging5plus": 7,
	"totalReq": 8
},
{
	"plant": "MXS2",
	"plantDesc": "MXS2-Monterrey Services WHS",
	"aging11": 1,
	"aging2": 1,
	"aging34": 1,
	"aging5plus": 18,
	"totalReq": 18
},
{
	"plant": "MXW1",
	"plantDesc": "MXW1-Mexico Warehouse",
	"aging11": 1,
	"aging2": 1,
	"aging34": 1,
	"aging5plus": 1,
	"totalReq": 2
},
{
	"plant": "MXW2",
	"plantDesc": "MXW2-Monterrey Warehouse",
	"aging11": 15,
	"aging2": 1,
	"aging34": 1,
	"aging5plus": 15,
	"totalReq": 31
},
{
	"plant": "NL11",
	"plantDesc": "NL11-Haaksbergen MFG Plant",
	"aging11": 54,
	"aging2": 7,
	"aging34": 24,
	"aging5plus": 143,
	"totalReq": 228
},
{
	"plant": "NLS1",
	"plantDesc": "NLS1-Haaksbergen After Market",
	"aging11": 1,
	"aging2": 4,
	"aging34": 3,
	"aging5plus": 11,
	"totalReq": 18
},
{
	"plant": "NLS9",
	"plantDesc": "NLS9-UPS AS&S Netherlands",
	"aging11": 6,
	"aging2": 7,
	"aging34": 1,
	"aging5plus": 2,
	"totalReq": 15
},
{
	"plant": "NLW9",
	"plantDesc": "NLW9-UPS Subsidiary Netherlands",
	"aging11": 1,
	"aging2": 1,
	"aging34": 1,
	"aging5plus": 2,
	"totalReq": 3
},
{
	"plant": "PL11",
	"plantDesc": "PL11-Klodzko MFG Plant",
	"aging11": 2229,
	"aging2": 183,
	"aging34": 424,
	"aging5plus": 1183,
	"totalReq": 4119
},
{
	"plant": "PL12",
	"plantDesc": "PL12-Bielsko-Biala MFG Plant",
	"aging11": 2438,
	"aging2": 48,
	"aging34": 268,
	"aging5plus": 813,
	"totalReq": 3567
},
{
	"plant": "PL13",
	"plantDesc": "PL13-Lodz MFG Plant",
	"aging11": 241,
	"aging2": 26,
	"aging34": 66,
	"aging5plus": 512,
	"totalReq": 835
},
{
	"plant": "PL19",
	"plantDesc": "PL19-UPS Bielsko-Biala",
	"aging11": 34,
	"aging2": 4,
	"aging34": 4,
	"aging5plus": 179,
	"totalReq": 221
},
{
	"plant": "PLS1",
	"plantDesc": "PLS1-After Market Poland",
	"aging11": 55,
	"aging2": 1,
	"aging34": 1,
	"aging5plus": 5,
	"totalReq": 61
},
{
	"plant": "PLS9",
	"plantDesc": "PLS9-UPS After Market Poland",
	"aging11": 5,
	"aging2": 43,
	"aging34": 2,
	"aging5plus": 14,
	"totalReq": 64
},
{
	"plant": "PR11",
	"plantDesc": "PR11-Arecibo MFG Plant",
	"aging11": 651,
	"aging2": 93,
	"aging34": 8,
	"aging5plus": 51,
	"totalReq": 813
},
{
	"plant": "PR12",
	"plantDesc": "PR12-San German MFG Plant",
	"aging11": 115,
	"aging2": 13,
	"aging34": 21,
	"aging5plus": 17,
	"totalReq": 156
},
{
	"plant": "PR13",
	"plantDesc": "PR13-Vieques MFG Plant",
	"aging11": 27,
	"aging2": 2,
	"aging34": 1,
	"aging5plus": 1,
	"totalReq": 29
},
{
	"plant": "PR14",
	"plantDesc": "PR14-Vega Baja MFG Plant",
	"aging11": 1,
	"aging2": 1,
	"aging34": 1,
	"aging5plus": 1,
	"totalReq": 1
},
{
	"plant": "PR15",
	"plantDesc": "PR15-Humacao MFG Plant",
	"aging11": 1,
	"aging2": 1,
	"aging34": 1,
	"aging5plus": 1,
	"totalReq": 1
},
{
	"plant": "PR16",
	"plantDesc": "PR16-Vega Alta MFG Plant",
	"aging11": 122,
	"aging2": 87,
	"aging34": 1,
	"aging5plus": 19,
	"totalReq": 229
},
{
	"plant": "PR17",
	"plantDesc": "PR17-Rating Plug MFG Plan",
	"aging11": 45,
	"aging2": 21,
	"aging34": 1,
	"aging5plus": 2,
	"totalReq": 67
},
{
	"plant": "SGW1",
	"plantDesc": "SGW1-GE Pacific Singapore WHSE1",
	"aging11": 47,
	"aging2": 2,
	"aging34": 1,
	"aging5plus": 253,
	"totalReq": 312
},
{
	"plant": "SGW2",
	"plantDesc": "SGW2-GE Pacific Singapore WHSE2",
	"aging11": 19,
	"aging2": 2,
	"aging34": 1,
	"aging5plus": 1,
	"totalReq": 21
},
{
	"plant": "TRW1",
	"plantDesc": "TRW1-GE Endustriyel Istanbul",
	"aging11": 2,
	"aging2": 1,
	"aging34": 1,
	"aging5plus": 1,
	"totalReq": 3
},
{
	"plant": "US11",
	"plantDesc": "US11-Plainville MFG Plant",
	"aging11": 1,
	"aging2": 1,
	"aging34": 1,
	"aging5plus": 2,
	"totalReq": 2
},
{
	"plant": "US12",
	"plantDesc": "US12-Burlington MFG Plant",
	"aging11": 28,
	"aging2": 16,
	"aging34": 5,
	"aging5plus": 78,
	"totalReq": 127
},
{
	"plant": "US13",
	"plantDesc": "US13-Mebane MFG Plant",
	"aging11": 185,
	"aging2": 21,
	"aging34": 11,
	"aging5plus": 88,
	"totalReq": 314
},
{
	"plant": "US14",
	"plantDesc": "US14-Selmer MFG Plant",
	"aging11": 12,
	"aging2": 2,
	"aging34": 1,
	"aging5plus": 41,
	"totalReq": 56
},
{
	"plant": "US15",
	"plantDesc": "US15-Auburn MFG Plant",
	"aging11": 13,
	"aging2": 6,
	"aging34": 8,
	"aging5plus": 39,
	"totalReq": 66
},
{
	"plant": "US16",
	"plantDesc": "US16-Morristown MFG Plant",
	"aging11": 117,
	"aging2": 41,
	"aging34": 31,
	"aging5plus": 33,
	"totalReq": 221
},
{
	"plant": "US17",
	"plantDesc": "US17-Equipment Direct Ship",
	"aging11": 19,
	"aging2": 2,
	"aging34": 1,
	"aging5plus": 26,
	"totalReq": 47
},
{
	"plant": "US18",
	"plantDesc": "US18-Seattle MFG Plant",
	"aging11": 1,
	"aging2": 6,
	"aging34": 1,
	"aging5plus": 1,
	"totalReq": 7
},
{
	"plant": "US11",
	"plantDesc": "US11-Nogales MFG Plant",
	"aging11": 784,
	"aging2": 115,
	"aging34": 37,
	"aging5plus": 131,
	"totalReq": 1167
},
{
	"plant": "US12",
	"plantDesc": "US12-Saltillo MFG Plant",
	"aging11": 554,
	"aging2": 2,
	"aging34": 2,
	"aging5plus": 33,
	"totalReq": 591
},
{
	"plant": "US13",
	"plantDesc": "US13-Monterrey EDESA MFG Plant",
	"aging11": 159,
	"aging2": 17,
	"aging34": 13,
	"aging5plus": 272,
	"totalReq": 461
},
{
	"plant": "US14",
	"plantDesc": "US14-Component Direct Ship",
	"aging11": 5,
	"aging2": 1,
	"aging34": 1,
	"aging5plus": 25,
	"totalReq": 31
},
{
	"plant": "US37",
	"plantDesc": "US37-Zenith Chicago MFG",
	"aging11": 1,
	"aging2": 1,
	"aging34": 1,
	"aging5plus": 4,
	"totalReq": 5
},
{
	"plant": "US41",
	"plantDesc": "US41-UPS Product Plano",
	"aging11": 3,
	"aging2": 1,
	"aging34": 2,
	"aging5plus": 11,
	"totalReq": 16
},
{
	"plant": "US44",
	"plantDesc": "US44-Anasco TVSS Resale",
	"aging11": 1,
	"aging2": 1,
	"aging34": 1,
	"aging5plus": 1,
	"totalReq": 1
},
{
	"plant": "USH1",
	"plantDesc": "USH1-US Headquarters",
	"aging11": 1,
	"aging2": 1,
	"aging34": 1,
	"aging5plus": 1,
	"totalReq": 1
},
{
	"plant": "USS2",
	"plantDesc": "USS2-Zenith Chicago AfterMarket",
	"aging11": 3,
	"aging2": 1,
	"aging34": 1,
	"aging5plus": 26,
	"totalReq": 29
},
{
	"plant": "USS3",
	"plantDesc": "USS3-UPS Mt.Juliet AfterMarket",
	"aging11": 15,
	"aging2": 2,
	"aging34": 1,
	"aging5plus": 13,
	"totalReq": 31
},
{
	"plant": "USW1",
	"plantDesc": "USW1-Midwest Irving",
	"aging11": 1,
	"aging2": 1,
	"aging34": 1,
	"aging5plus": 1,
	"totalReq": 1
},
{
	"plant": "USW1",
	"plantDesc": "USW1-Mount Juliet WHSE",
	"aging11": 12,
	"aging2": 8,
	"aging34": 3,
	"aging5plus": 27,
	"totalReq": 51
},
{
	"plant": "USW2",
	"plantDesc": "USW2-Mt. Juliet - Consumer WHSE",
	"aging11": 1,
	"aging2": 1,
	"aging34": 1,
	"aging5plus": 1,
	"totalReq": 1
},
{
	"plant": "USW3",
	"plantDesc": "USW3-Mira Loma WHSE",
	"aging11": 1,
	"aging2": 1,
	"aging34": 1,
	"aging5plus": 1,
	"totalReq": 1
},
{
	"plant": "USW4",
	"plantDesc": "USW4-Miami WHSE",
	"aging11": 1,
	"aging2": 4,
	"aging34": 1,
	"aging5plus": 5,
	"totalReq": 11
},
{
	"plant": "USW6",
	"plantDesc": "USW6-Carolina WHSE",
	"aging11": 1,
	"aging2": 1,
	"aging34": 1,
	"aging5plus": 1,
	"totalReq": 1
},
{
	"plant": "USW7",
	"plantDesc": "USW7-Midwest Farmingdale",
	"aging11": 1,
	"aging2": 1,
	"aging34": 1,
	"aging5plus": 1,
	"totalReq": 1
},
{
	"plant": "USW8",
	"plantDesc": "USW8-Midwest Denver",
	"aging11": 1,
	"aging2": 6,
	"aging34": 1,
	"aging5plus": 1,
	"totalReq": 6
},
{
	"plant": "USW9",
	"plantDesc": "USW9-Midwest Deerfield Be",
	"aging11": 1,
	"aging2": 1,
	"aging34": 1,
	"aging5plus": 1,
	"totalReq": 1
},
{
	"plant": "USWG",
	"plantDesc": "USWG-Midwest Louisville",
	"aging11": 1,
	"aging2": 1,
	"aging34": 1,
	"aging5plus": 1,
	"totalReq": 1
},
{
	"plant": "USWH",
	"plantDesc": "USWH-Midwest Detroit",
	"aging11": 1,
	"aging2": 1,
	"aging34": 1,
	"aging5plus": 1,
	"totalReq": 1
},
{
	"plant": "ZA11",
	"plantDesc": "ZA11-GE South Africa",
	"aging11": 1,
	"aging2": 2,
	"aging34": 1,
	"aging5plus": 61,
	"totalReq": 62
},
{
	"plant": "ZAS1",
	"plantDesc": "ZAS1-GE South Africa SA&S",
	"aging11": 1,
	"aging2": 1,
	"aging34": 1,
	"aging5plus": 37,
	"totalReq": 37
}]